conflag/__init__.py
conflag/decorator.py
conflag/help.py
conflag/run.py
conflag/state/__init__.py
conflag/state/annotations.py
conflag/state/argument.py
conflag/state/command.py
conflag/state/option.py
conflag/state/state.py
conflag-0.0.3.dist-info/METADATA
conflag-0.0.3.dist-info/WHEEL
conflag-0.0.3.dist-info/RECORD
