Metadata-Version: 2.1
Name: conflag
Version: 0.0.3
Summary: A tool to help me combine configuration files and flags in my scripts.
Author: leomar
Requires-Python: >=3.12,<4.0
Classifier: Programming Language :: Python :: 3
Classifier: Programming Language :: Python :: 3.12
Requires-Dist: pytest (>=8.3.2,<9.0.0)
